[
  {
    "id": 1,
    "name": "Neuro Desk",
    "price": 30.99,
    "photo": "../../assets/beauty.jpg"
  },
  {
    "id": 2,
    "name": "Neuro Window",
    "price": 30.99,
    "photo": "../../assets/apple.jpg"
  },
  {
    "id": 3,
    "name": "Neuro Space",
    "price": 30.99,
    "photo": "../../assets/white.jpg"
  },
  {
    "id": 4,
    "name": "Neuro Chair",
    "price": 30.99,
    "photo": "../../assets/table.jpg"
  },
  {
    "id": 5,
    "name": "Neuro Table",
    "price": 30.99,
    "photo": "../../assets/piano.jpg"
  },
  {
    "id": 6,
    "name": "Neuro Room",
    "price": 30.99,
    "photo": "../../assets/dog.jpg"
  }
]